dc_parser/nkutil.py
dc_parser/parse_nk.py
dc_parser/__init__.py
dc_parser/trees.py
dc_parser/parse.py
dc_parser/chart_helper.cpython-311-x86_64-linux-gnu.so
dc_parser/utils.py
dc_parser/vocabulary.py
disfluency_constituency_parser-0.0.12.dist-info/RECORD
disfluency_constituency_parser-0.0.12.dist-info/WHEEL
disfluency_constituency_parser-0.0.12.dist-info/top_level.txt
disfluency_constituency_parser-0.0.12.dist-info/LICENSE
disfluency_constituency_parser-0.0.12.dist-info/METADATA
