Metadata-Version: 2.1
Name: disfluency-constituency-parser
Version: 0.0.12
Home-page: https://github.com/liwangd/disfluency-constituency-parser
Author: Li Wang
Author-email: li@liwang.info
Classifier: Programming Language :: Python :: 2.7
Classifier: Programming Language :: Python :: 3
Classifier: License :: OSI Approved :: MIT License
Classifier: Operating System :: OS Independent
Classifier: Topic :: Scientific/Engineering :: Artificial Intelligence
Classifier: Topic :: Text Processing :: Linguistic
License-File: LICENSE
Requires-Dist: cython
Requires-Dist: numpy
Requires-Dist: nltk (>=3.2)
